influxed/__init__.py
influxed/ifql/__init__.py
influxed/ifql/column.py
influxed/ifql/create_statement.py
influxed/ifql/exceptions.py
influxed/ifql/filter.py
influxed/ifql/functions.py
influxed/ifql/grant_statement.py
influxed/ifql/infix_operators.py
influxed/ifql/insert_statement.py
influxed/ifql/revoke_statement.py
influxed/ifql/select_statement.py
influxed/ifql/show_statement.py
influxed/ifql/statement.py
influxed/ifql/util.py
influxed/ifql/line_protocol/__init__.py
influxed/ifql/line_protocol/dataframe_to_line.py
influxed/ifql/line_protocol/dict_to_line.py
influxed/ifql/line_protocol/list_to_line.py
influxed/ifql/line_protocol/series_to_line.py
influxed/mediator/__init__.py
influxed/mediator/exceptions.py
influxed/mediator/influx_client.py
influxed/mediator/mediator.py
influxed/mediator/response_parser.py
influxed/mediator/retry_strategies.py
influxed/mediator/client_wrappers/__init__.py
influxed/mediator/client_wrappers/requests_wrapper.py
influxed/orm/__init__.py
influxed/orm/database.py
influxed/orm/engine.py
influxed/orm/exceptions.py
influxed/orm/influx_server.py
influxed/orm/measurement.py
influxed/orm/capabilities/__init__.py
influxed/orm/capabilities/asyncable.py
influxed/orm/capabilities/createable.py
influxed/orm/capabilities/executable.py
influxed/orm/capabilities/insertable.py
influxed/orm/capabilities/queryable.py
influxed/orm/capabilities/showable.py
influxed/orm/columns/__init__.py
influxed/orm/columns/fieldkey.py
influxed/orm/columns/tagkey.py
influxed/orm/declarative/__init__.py
influxed/orm/declarative/declarative_base.py
influxed-0.1.5.2.dist-info/LICENSE
influxed-0.1.5.2.dist-info/METADATA
influxed-0.1.5.2.dist-info/WHEEL
influxed-0.1.5.2.dist-info/top_level.txt
influxed-0.1.5.2.dist-info/RECORD
