Metadata-Version: 2.1
Name: influxed
Version: 0.1.5.2
Summary: Inlfuxed influx query language and orm
Home-page: https://gitlab.com/Romeren/influxed/
Author: Emil S Roemer
Author-email: emilromer@hotmail.com
License: UNKNOWN
Keywords: Influx InfluxDb Query Language QL ORM
Platform: UNKNOWN
Classifier: Development Status :: 3 - Alpha
Classifier: Intended Audience :: Developers
Classifier: Programming Language :: Python :: 3
Classifier: License :: OSI Approved :: GNU General Public License v3 or later (GPLv3+) 
Classifier: Operating System :: OS Independent
Requires-Dist: pandas
Requires-Dist: requests
